moviehub/__init__.py
moviehub/console.py
moviehub/moviehub.py
moviehub-1.0.1.dist-info/DESCRIPTION.rst
moviehub-1.0.1.dist-info/METADATA
moviehub-1.0.1.dist-info/RECORD
moviehub-1.0.1.dist-info/WHEEL
moviehub-1.0.1.dist-info/entry_points.txt
moviehub-1.0.1.dist-info/metadata.json
moviehub-1.0.1.dist-info/top_level.txt
