Metadata-Version: 2.0
Name: moviehub
Version: 1.0.1
Summary: A console application for obtaining movie information using OMDb API
Home-page: https://github.com/chunkhang/moviehub
Author: Marcus Mu
Author-email: chunkhang@gmail.com
License: UNLICENSE
Keywords: movie,hub,omdb
Platform: UNKNOWN
Classifier: Intended Audience :: End Users/Desktop
Classifier: Programming Language :: Python :: 3 :: Only
Classifier: Environment :: Console
Requires-Dist: beautifulsoup4
Requires-Dist: requests
